p2d2/__init__.py
p2d2/pkg_database/__init__.py
p2d2/pkg_database/mod_cron.py
p2d2/pkg_database/mod_cron_models.py
p2d2/pkg_database/mod_crud.py
p2d2/pkg_database/mod_database.py
p2d2/pkg_database/mod_database_models.py
p2d2/pkg_database/mod_database_resources.py
p2d2/pkg_database/mod_schema.py
p2d2/pkg_database/pkg_cron_files/__init__.py
p2d2/pkg_database/pkg_cron_files/mod_autosave.py
p2d2/pkg_database/pkg_cron_files/mod_backup.py
p2d2/pkg_database/pkg_pkl/__init__.py
p2d2/pkg_database/pkg_pkl/mod_pkl_changelog.py
p2d2/pkg_database/pkg_util/__init__.py
p2d2/pkg_database/pkg_util/mod_analytics.py
p2d2/pkg_database/pkg_util/mod_table_index.py
p2d2-0.1.132.dist-info/licenses/LICENSE
p2d2-0.1.132.dist-info/METADATA
p2d2-0.1.132.dist-info/WHEEL
p2d2-0.1.132.dist-info/RECORD
