Metadata-Version: 2.4
Name: p2d2
Version: 0.1.132
Summary: Pickled Parquetted Dataframed Database
License-File: LICENSE
Author: Miles Copeland Luce
Requires-Python: >=3.13,<4.0
Classifier: Programming Language :: Python :: 3
Classifier: Programming Language :: Python :: 3.13
Classifier: Programming Language :: Python :: 3.14
Requires-Dist: annotated-dict (>=0.1.0,<0.2.0)
Requires-Dist: ezmq (>=2025.10.29.0,<2026.0.0.0)
Requires-Dist: fastparquet (>=2024.11.0,<2025.0.0)
Requires-Dist: loguru (>=0.7.3,<0.8.0)
Requires-Dist: pandas (>=2.3.3,<3.0.0)
Requires-Dist: toomanyconfigs (>=0.2.82,<0.3.0)
